Workbook

Sheet Inicio
B2: Stock y ventas para tu negocio
B3: Para kioscos, almacenes, ferreterías, tiendas o emprendimientos: cuánto te queda de cada producto, qué tenés que reponer y cuánto ganaste.
B5: Cómo se usa
B6: • Hoja "Productos": cargá cada producto con su código, costo, precio de venta, stock inicial y stock mínimo.
B7: • Hoja "Movimientos": cada vez que entra mercadería o vendés, una fila con el código, el tipo (Entrada o Venta) y la cantidad.
B8: • En "Productos" se calcula solo el stock actual, y aparece "REPONER" cuando baja del mínimo.
B9: • Hoja "Ventas del mes": elegí mes y año, y ves cuánto vendiste y cuánto ganaste.
B11: Celdas amarillas con texto azul = las completás vos. El resto se calcula solo: no lo borres.
B13: Si te sirvió y querés colaborar, mi alias de Mercado Pago es igna.pelliza. Gracias.
B14: Plantilla gratuita hecha en San Juan, Argentina. Podés usarla y compartirla. Revisá siempre tus números: es una herramienta de ayuda.

Sheet Productos
A1: Código | B1: Producto | C1: Costo ($) | D1: Precio de venta ($) | E1: Ganancia por unidad | F1: Stock inicial | G1: Stock mínimo | H1: Entradas | I1: Vendidos | J1: Stock actual | K1: Estado
A2: A001 | B2: Gaseosa 2,25 L (ejemplo) | C2: 1800 | D2: 2600 | E2: =IF(A2="","",D2-C2) | F2: 24 | G2: 6 | H2: =IF(A2="","",SUMIFS(Movimientos!$D$2:$D$3001,Movimientos!$B$2:$B$3001,A2,Movimientos!$C$2:$C$3001,"Entrada")) | I2: =IF(A2="","",SUMIFS(Movimientos!$D$2:$D$3001,Movimientos!$B$2:$B$3001,A2,Movimientos!$C$2:$C$3001,"Venta")) | J2: =IF(A2="","",F2+H2-I2) | K2: =IF(A2="","",IF(J2<=G2,"REPONER","OK"))
E3: =IF(A3="","",D3-C3) | H3: =IF(A3="","",SUMIFS(Movimientos!$D$2:$D$3001,Movimientos!$B$2:$B$3001,A3,Movimientos!$C$2:$C$3001,"Entrada")) | I3: =IF(A3="","",SUMIFS(Movimientos!$D$2:$D$3001,Movimientos!$B$2:$B$3001,A3,Movimientos!$C$2:$C$3001,"Venta")) | J3: =IF(A3="","",F3+H3-I3) | K3: =IF(A3="","",IF(J3<=G3,"REPONER","OK"))
E4: =IF(A4="","",D4-C4) | H4: =IF(A4="","",SUMIFS(Movimientos!$D$2:$D$3001,Movimientos!$B$2:$B$3001,A4,Movimientos!$C$2:$C$3001,"Entrada")) | I4: =IF(A4="","",SUMIFS(Movimientos!$D$2:$D$3001,Movimientos!$B$2:$B$3001,A4,Movimientos!$C$2:$C$3001,"Venta")) | J4: =IF(A4="","",F4+H4-I4) | K4: =IF(A4="","",IF(J4<=G4,"REPONER","OK"))
E5: =IF(A5="","",D5-C5) | H5: =IF(A5="","",SUMIFS(Movimientos!$D$2:$D$3001,Movimientos!$B$2:$B$3001,A5,Movimientos!$C$2:$C$3001,"Entrada")) | I5: =IF(A5="","",SUMIFS(Movimientos!$D$2:$D$3001,Movimientos!$B$2:$B$3001,A5,Movimientos!$C$2:$C$3001,"Venta")) | J5: =IF(A5="","",F5+H5-I5) | K5: =IF(A5="","",IF(J5<=G5,"REPONER","OK"))
E6: =IF(A6="","",D6-C6) | H6: =IF(A6="","",SUMIFS(Movimientos!$D$2:$D$3001,Movimientos!$B$2:$B$3001,A6,Movimientos!$C$2:$C$3001,"Entrada")) | I6: =IF(A6="","",SUMIFS(Movimientos!$D$2:$D$3001,Movimientos!$B$2:$B$3001,A6,Movimientos!$C$2:$C$3001,"Venta")) | J6: =IF(A6="","",F6+H6-I6) | K6: =IF(A6="","",IF(J6<=G6,"REPONER","OK"))
E7: =IF(A7="","",D7-C7) | H7: =IF(A7="","",SUMIFS(Movimientos!$D$2:$D$3001,Movimientos!$B$2:$B$3001,A7,Movimientos!$C$2:$C$3001,"Entrada")) | I7: =IF(A7="","",SUMIFS(Movimientos!$D$2:$D$3001,Movimientos!$B$2:$B$3001,A7,Movimientos!$C$2:$C$3001,"Venta")) | J7: =IF(A7="","",F7+H7-I7) | K7: =IF(A7="","",IF(J7<=G7,"REPONER","OK"))
E8: =IF(A8="","",D8-C8) | H8: =IF(A8="","",SUMIFS(Movimientos!$D$2:$D$3001,Movimientos!$B$2:$B$3001,A8,Movimientos!$C$2:$C$3001,"Entrada")) | I8: =IF(A8="","",SUMIFS(Movimientos!$D$2:$D$3001,Movimientos!$B$2:$B$3001,A8,Movimientos!$C$2:$C$3001,"Venta")) | J8: =IF(A8="","",F8+H8-I8) | K8: =IF(A8="","",IF(J8<=G8,"REPONER","OK"))
E9: =IF(A9="","",D9-C9) | H9: =IF(A9="","",SUMIFS(Movimientos!$D$2:$D$3001,Movimientos!$B$2:$B$3001,A9,Movimientos!$C$2:$C$3001,"Entrada")) | I9: =IF(A9="","",SUMIFS(Movimientos!$D$2:$D$3001,Movimientos!$B$2:$B$3001,A9,Movimientos!$C$2:$C$3001,"Venta")) | J9: =IF(A9="","",F9+H9-I9) | K9: =IF(A9="","",IF(J9<=G9,"REPONER","OK"))
E10: =IF(A10="","",D10-C10) | H10: =IF(A10="","",SUMIFS(Movimientos!$D$2:$D$3001,Movimientos!$B$2:$B$3001,A10,Movimientos!$C$2:$C$3001,"Entrada")) | I10: =IF(A10="","",SUMIFS(Movimientos!$D$2:$D$3001,Movimientos!$B$2:$B$3001,A10,Movimientos!$C$2:$C$3001,"Venta")) | J10: =IF(A10="","",F10+H10-I10) | K10: =IF(A10="","",IF(J10<=G10,"REPONER","OK"))
E11: =IF(A11="","",D11-C11) | H11: =IF(A11="","",SUMIFS(Movimientos!$D$2:$D$3001,Movimientos!$B$2:$B$3001,A11,Movimientos!$C$2:$C$3001,"Entrada")) | I11: =IF(A11="","",SUMIFS(Movimientos!$D$2:$D$3001,Movimientos!$B$2:$B$3001,A11,Movimientos!$C$2:$C$3001,"Venta")) | J11: =IF(A11="","",F11+H11-I11) | K11: =IF(A11="","",IF(J11<=G11,"REPONER","OK"))
E12: =IF(A12="","",D12-C12) | H12: =IF(A12="","",SUMIFS(Movimientos!$D$2:$D$3001,Movimientos!$B$2:$B$3001,A12,Movimientos!$C$2:$C$3001,"Entrada")) | I12: =IF(A12="","",SUMIFS(Movimientos!$D$2:$D$3001,Movimientos!$B$2:$B$3001,A12,Movimientos!$C$2:$C$3001,"Venta")) | J12: =IF(A12="","",F12+H12-I12) | K12: =IF(A12="","",IF(J12<=G12,"REPONER","OK"))
E13: =IF(A13="","",D13-C13) | H13: =IF(A13="","",SUMIFS(Movimientos!$D$2:$D$3001,Movimientos!$B$2:$B$3001,A13,Movimientos!$C$2:$C$3001,"Entrada")) | I13: =IF(A13="","",SUMIFS(Movimientos!$D$2:$D$3001,Movimientos!$B$2:$B$3001,A13,Movimientos!$C$2:$C$3001,"Venta")) | J13: =IF(A13="","",F13+H13-I13) | K13: =IF(A13="","",IF(J13<=G13,"REPONER","OK"))
E14: =IF(A14="","",D14-C14) | H14: =IF(A14="","",SUMIFS(Movimientos!$D$2:$D$3001,Movimientos!$B$2:$B$3001,A14,Movimientos!$C$2:$C$3001,"Entrada")) | I14: =IF(A14="","",SUMIFS(Movimientos!$D$2:$D$3001,Movimientos!$B$2:$B$3001,A14,Movimientos!$C$2:$C$3001,"Venta")) | J14: =IF(A14="","",F14+H14-I14) | K14: =IF(A14="","",IF(J14<=G14,"REPONER","OK"))
... E501: =IF(A501="","",D501-C501) | H501: =IF(A501="","",SUMIFS(Movimientos!$D$2:$D$3001,Movimientos!$B$2:$B$3001,A501,Movimientos!$C$2:$C$3001,"Entrada")) | I501: =IF(A501="","",SUMIFS(Movimientos!$D$2:$D$3001,Movimientos!$B$2:$B$3001,A501,Movimientos!$C$2:$C$3001,"Venta")) | J501: =IF(A501="","",F501+H501-I501) | K501: =IF(A501="","",IF(J501<=G501,"REPONER","OK"))

Sheet Movimientos
A1: Fecha | B1: Código | C1: Tipo | D1: Cantidad | E1: Producto | F1: Importe de venta ($) | G1: Ganancia ($) | H1: Mes | I1: Año
A2: 46318 | B2: A001 | C2: Venta | D2: 3 | E2: =IF(B2="","",IFERROR(INDEX(Productos!$B$2:$B$501,MATCH(B2,Productos!$A$2:$A$501,0)),"¿Código?")) | F2: =IF(C2<>"Venta","",D2*IFERROR(INDEX(Productos!$D$2:$D$501,MATCH(B2,Productos!$A$2:$A$501,0)),0)) | G2: =IF(C2<>"Venta","",D2*IFERROR(INDEX(Productos!$E$2:$E$501,MATCH(B2,Productos!$A$2:$A$501,0)),0)) | H2: =IF(A2="","",MONTH(A2)) | I2: =IF(A2="","",YEAR(A2))
E3: =IF(B3="","",IFERROR(INDEX(Productos!$B$2:$B$501,MATCH(B3,Productos!$A$2:$A$501,0)),"¿Código?")) | F3: =IF(C3<>"Venta","",D3*IFERROR(INDEX(Productos!$D$2:$D$501,MATCH(B3,Productos!$A$2:$A$501,0)),0)) | G3: =IF(C3<>"Venta","",D3*IFERROR(INDEX(Productos!$E$2:$E$501,MATCH(B3,Productos!$A$2:$A$501,0)),0)) | H3: =IF(A3="","",MONTH(A3)) | I3: =IF(A3="","",YEAR(A3))
E4: =IF(B4="","",IFERROR(INDEX(Productos!$B$2:$B$501,MATCH(B4,Productos!$A$2:$A$501,0)),"¿Código?")) | F4: =IF(C4<>"Venta","",D4*IFERROR(INDEX(Productos!$D$2:$D$501,MATCH(B4,Productos!$A$2:$A$501,0)),0)) | G4: =IF(C4<>"Venta","",D4*IFERROR(INDEX(Productos!$E$2:$E$501,MATCH(B4,Productos!$A$2:$A$501,0)),0)) | H4: =IF(A4="","",MONTH(A4)) | I4: =IF(A4="","",YEAR(A4))
E5: =IF(B5="","",IFERROR(INDEX(Productos!$B$2:$B$501,MATCH(B5,Productos!$A$2:$A$501,0)),"¿Código?")) | F5: =IF(C5<>"Venta","",D5*IFERROR(INDEX(Productos!$D$2:$D$501,MATCH(B5,Productos!$A$2:$A$501,0)),0)) | G5: =IF(C5<>"Venta","",D5*IFERROR(INDEX(Productos!$E$2:$E$501,MATCH(B5,Productos!$A$2:$A$501,0)),0)) | H5: =IF(A5="","",MONTH(A5)) | I5: =IF(A5="","",YEAR(A5))
E6: =IF(B6="","",IFERROR(INDEX(Productos!$B$2:$B$501,MATCH(B6,Productos!$A$2:$A$501,0)),"¿Código?")) | F6: =IF(C6<>"Venta","",D6*IFERROR(INDEX(Productos!$D$2:$D$501,MATCH(B6,Productos!$A$2:$A$501,0)),0)) | G6: =IF(C6<>"Venta","",D6*IFERROR(INDEX(Productos!$E$2:$E$501,MATCH(B6,Productos!$A$2:$A$501,0)),0)) | H6: =IF(A6="","",MONTH(A6)) | I6: =IF(A6="","",YEAR(A6))
E7: =IF(B7="","",IFERROR(INDEX(Productos!$B$2:$B$501,MATCH(B7,Productos!$A$2:$A$501,0)),"¿Código?")) | F7: =IF(C7<>"Venta","",D7*IFERROR(INDEX(Productos!$D$2:$D$501,MATCH(B7,Productos!$A$2:$A$501,0)),0)) | G7: =IF(C7<>"Venta","",D7*IFERROR(INDEX(Productos!$E$2:$E$501,MATCH(B7,Productos!$A$2:$A$501,0)),0)) | H7: =IF(A7="","",MONTH(A7)) | I7: =IF(A7="","",YEAR(A7))
E8: =IF(B8="","",IFERROR(INDEX(Productos!$B$2:$B$501,MATCH(B8,Productos!$A$2:$A$501,0)),"¿Código?")) | F8: =IF(C8<>"Venta","",D8*IFERROR(INDEX(Productos!$D$2:$D$501,MATCH(B8,Productos!$A$2:$A$501,0)),0)) | G8: =IF(C8<>"Venta","",D8*IFERROR(INDEX(Productos!$E$2:$E$501,MATCH(B8,Productos!$A$2:$A$501,0)),0)) | H8: =IF(A8="","",MONTH(A8)) | I8: =IF(A8="","",YEAR(A8))
E9: =IF(B9="","",IFERROR(INDEX(Productos!$B$2:$B$501,MATCH(B9,Productos!$A$2:$A$501,0)),"¿Código?")) | F9: =IF(C9<>"Venta","",D9*IFERROR(INDEX(Productos!$D$2:$D$501,MATCH(B9,Productos!$A$2:$A$501,0)),0)) | G9: =IF(C9<>"Venta","",D9*IFERROR(INDEX(Productos!$E$2:$E$501,MATCH(B9,Productos!$A$2:$A$501,0)),0)) | H9: =IF(A9="","",MONTH(A9)) | I9: =IF(A9="","",YEAR(A9))
E10: =IF(B10="","",IFERROR(INDEX(Productos!$B$2:$B$501,MATCH(B10,Productos!$A$2:$A$501,0)),"¿Código?")) | F10: =IF(C10<>"Venta","",D10*IFERROR(INDEX(Productos!$D$2:$D$501,MATCH(B10,Productos!$A$2:$A$501,0)),0)) | G10: =IF(C10<>"Venta","",D10*IFERROR(INDEX(Productos!$E$2:$E$501,MATCH(B10,Productos!$A$2:$A$501,0)),0)) | H10: =IF(A10="","",MONTH(A10)) | I10: =IF(A10="","",YEAR(A10))
E11: =IF(B11="","",IFERROR(INDEX(Productos!$B$2:$B$501,MATCH(B11,Productos!$A$2:$A$501,0)),"¿Código?")) | F11: =IF(C11<>"Venta","",D11*IFERROR(INDEX(Productos!$D$2:$D$501,MATCH(B11,Productos!$A$2:$A$501,0)),0)) | G11: =IF(C11<>"Venta","",D11*IFERROR(INDEX(Productos!$E$2:$E$501,MATCH(B11,Productos!$A$2:$A$501,0)),0)) | H11: =IF(A11="","",MONTH(A11)) | I11: =IF(A11="","",YEAR(A11))
E12: =IF(B12="","",IFERROR(INDEX(Productos!$B$2:$B$501,MATCH(B12,Productos!$A$2:$A$501,0)),"¿Código?")) | F12: =IF(C12<>"Venta","",D12*IFERROR(INDEX(Productos!$D$2:$D$501,MATCH(B12,Productos!$A$2:$A$501,0)),0)) | G12: =IF(C12<>"Venta","",D12*IFERROR(INDEX(Productos!$E$2:$E$501,MATCH(B12,Productos!$A$2:$A$501,0)),0)) | H12: =IF(A12="","",MONTH(A12)) | I12: =IF(A12="","",YEAR(A12))
E13: =IF(B13="","",IFERROR(INDEX(Productos!$B$2:$B$501,MATCH(B13,Productos!$A$2:$A$501,0)),"¿Código?")) | F13: =IF(C13<>"Venta","",D13*IFERROR(INDEX(Productos!$D$2:$D$501,MATCH(B13,Productos!$A$2:$A$501,0)),0)) | G13: =IF(C13<>"Venta","",D13*IFERROR(INDEX(Productos!$E$2:$E$501,MATCH(B13,Productos!$A$2:$A$501,0)),0)) | H13: =IF(A13="","",MONTH(A13)) | I13: =IF(A13="","",YEAR(A13))
E14: =IF(B14="","",IFERROR(INDEX(Productos!$B$2:$B$501,MATCH(B14,Productos!$A$2:$A$501,0)),"¿Código?")) | F14: =IF(C14<>"Venta","",D14*IFERROR(INDEX(Productos!$D$2:$D$501,MATCH(B14,Productos!$A$2:$A$501,0)),0)) | G14: =IF(C14<>"Venta","",D14*IFERROR(INDEX(Productos!$E$2:$E$501,MATCH(B14,Productos!$A$2:$A$501,0)),0)) | H14: =IF(A14="","",MONTH(A14)) | I14: =IF(A14="","",YEAR(A14))
... E3001: =IF(B3001="","",IFERROR(INDEX(Productos!$B$2:$B$501,MATCH(B3001,Productos!$A$2:$A$501,0)),"¿Código?")) | F3001: =IF(C3001<>"Venta","",D3001*IFERROR(INDEX(Productos!$D$2:$D$501,MATCH(B3001,Productos!$A$2:$A$501,0)),0)) | G3001: =IF(C3001<>"Venta","",D3001*IFERROR(INDEX(Productos!$E$2:$E$501,MATCH(B3001,Productos!$A$2:$A$501,0)),0)) | H3001: =IF(A3001="","",MONTH(A3001)) | I3001: =IF(A3001="","",YEAR(A3001))

Sheet Ventas del mes
A1: Ventas del mes
A3: Mes (1 a 12): | B3: 10
A4: Año: | B4: 2026
A6: Total vendido | B6: =SUMIFS(Movimientos!$F$2:$F$3001,Movimientos!$H$2:$H$3001,$B$3,Movimientos!$I$2:$I$3001,$B$4)
A7: Ganancia (precio - costo) | B7: =SUMIFS(Movimientos!$G$2:$G$3001,Movimientos!$H$2:$H$3001,$B$3,Movimientos!$I$2:$I$3001,$B$4)
A8: Unidades vendidas | B8: =SUMIFS(Movimientos!$D$2:$D$3001,Movimientos!$C$2:$C$3001,"Venta",Movimientos!$H$2:$H$3001,$B$3,Movimientos!$I$2:$I$3001,$B$4)
A9: Productos para reponer | B9: =COUNTIF(Productos!$K$2:$K$501,"REPONER")
A12: ¿Te sirvió? Alias de Mercado Pago: igna.pelliza
