Workbook

Sheet Inicio
B2: Presupuesto para oficios
B3: Para electricistas, plomeros, gasistas, albañiles, pintores, técnicos y cualquier oficio: armá un presupuesto prolijo, imprimilo o guardalo en PDF y mandalo por WhatsApp.
B5: Cómo se usa
B6: • Hoja "Mis datos": tu nombre, oficio, teléfono y condiciones. Se cargan una sola vez.
B7: • Hoja "Presupuesto": completá los datos del cliente y los ítems (materiales y mano de obra). Los totales se calculan solos.
B8: • Para mandarlo: Archivo → Guardar como PDF (o Imprimir → PDF), y lo enviás por WhatsApp o correo.
B9: • Para el próximo cliente: duplicá la hoja "Presupuesto" (clic derecho en la pestaña → Mover o copiar → Crear una copia).
B11: Celdas amarillas con texto azul = las completás vos. El resto se calcula solo: no lo borres.
B13: ¿Te sirvió? Invitame un café 🙌 Alias de Mercado Pago: igna.pelliza
B14: Plantilla gratuita hecha en San Juan, Argentina. Podés usarla y compartirla. Revisá siempre tus números: es una herramienta de ayuda.

Sheet Presupuesto
A1: ='Mis datos'!B1 -> Juan Pérez (ejemplo) | D1: PRESUPUESTO
A2: ='Mis datos'!B2&" · "&'Mis datos'!B3&" · "&'Mis datos'!B5 -> Electricista matriculado · 264 000-0000 · Gran San Juan | D2: N° | E2: 1
D3: Fecha | E3: 46318
A5: Cliente: | B5: Nombre del cliente
A6: Dirección: | B6: Dirección de la obra
A7: Trabajo: | B7: Instalación de 4 bocas y tablero (ejemplo)
A9: # | B9: Detalle | C9: Cantidad | D9: Precio unitario ($) | E9: Subtotal ($)
A10: 1 | B10: Cable 2,5 mm (rollo 100 m) | C10: 1 | D10: 95000 | E10: =IF(OR(C10="",D10=""),"",C10*D10) -> 95000
A11: 2 | B11: Mano de obra por boca | C11: 4 | D11: 30000 | E11: =IF(OR(C11="",D11=""),"",C11*D11) -> 120000
A12: 3 | E12: =IF(OR(C12="",D12=""),"",C12*D12)
A13: 4 | E13: =IF(OR(C13="",D13=""),"",C13*D13)
A14: 5 | E14: =IF(OR(C14="",D14=""),"",C14*D14)
A15: 6 | E15: =IF(OR(C15="",D15=""),"",C15*D15)
A16: 7 | E16: =IF(OR(C16="",D16=""),"",C16*D16)
A17: 8 | E17: =IF(OR(C17="",D17=""),"",C17*D17)
A18: 9 | E18: =IF(OR(C18="",D18=""),"",C18*D18)
A19: 10 | E19: =IF(OR(C19="",D19=""),"",C19*D19)
A20: 11 | E20: =IF(OR(C20="",D20=""),"",C20*D20)
A21: 12 | E21: =IF(OR(C21="",D21=""),"",C21*D21)
A22: 13 | E22: =IF(OR(C22="",D22=""),"",C22*D22)
A23: 14 | E23: =IF(OR(C23="",D23=""),"",C23*D23)
... A29: 20 | E29: =IF(OR(C29="",D29=""),"",C29*D29)
D31: Subtotal | E31: =SUM(E10:E29) -> 215000
D32: Descuento (%) | E32: 0
D33: TOTAL | E33: =E31*(1-E32) -> 215000
A35: ="Forma de pago: "&'Mis datos'!B7 -> Forma de pago: 50% al empezar, 50% al terminar. Efectivo o transferencia.
A36: ="Garantía: "&'Mis datos'!B8 -> Garantía: 3 meses sobre la mano de obra.
A37: ="Presupuesto válido por "&'Mis datos'!B6&" días desde la fecha." -> Presupuesto válido por 15 días desde la fecha.

Sheet Mis datos
A1: Nombre | B1: Juan Pérez (ejemplo)
A2: Oficio | B2: Electricista matriculado
A3: Teléfono / WhatsApp | B3: 264 000-0000
A4: Correo | B4: juan@ejemplo.com
A5: Zona | B5: Gran San Juan
A6: Validez del presupuesto (días) | B6: 15
A7: Forma de pago | B7: 50% al empezar, 50% al terminar. Efectivo o transferencia.
A8: Garantía | B8: 3 meses sobre la mano de obra.
